MANIFEST.in
README.md
requirements.txt
setup.cfg
setup.py
cow_csvw.egg-info/PKG-INFO
cow_csvw.egg-info/SOURCES.txt
cow_csvw.egg-info/dependency_links.txt
cow_csvw.egg-info/entry_points.txt
cow_csvw.egg-info/requires.txt
cow_csvw.egg-info/top_level.txt
src/csvw_gui.py
src/csvw_tool.py
src/__pycache__/csvw_gui.cpython-311.pyc
src/__pycache__/csvw_tool.cpython-311.pyc
src/assets/frame0/button_1.png
src/assets/frame0/button_2.png
src/assets/frame0/button_3.png
src/assets/frame0/button_4.png
src/assets/frame0/button_5.png
src/assets/frame0/entry_1.png
src/assets/frame0/entry_2.png
src/converter/csvw.py
src/converter/__pycache__/csvw.cpython-311.pyc
src/converter/util/__init__.py
src/converter/util/namespaces.yaml
src/converter/util/__pycache__/__init__.cpython-311.pyc