Metadata-Version: 2.1
Name: cow-csvw
Version: 2.0.0
Summary: Integrated CSV to RDF converter, using CSVW and nanopublications
Home-page: https://github.com/CLARIAH/COW
Download-URL: https://github.com/CLARIAH/COW/archive/2.0.0.tar.gz
Author: Albert Meroño-Peñuela, Roderick van der Weerdt, Rinke Hoekstra, Kathrin Dentler, Auke Rijpma, Richard Zijdeman, Melvin Roest, Xander Wilcke
Author-email: albert.merono@vu.nl
License: MIT
Keywords: csv,rdf,csvw
Classifier: License :: OSI Approved :: MIT License
Classifier: Programming Language :: Python
Classifier: Programming Language :: Python :: 3.10
